viabel/__init__.py
viabel/_distributions.py
viabel/_mc_diagnostics.py
viabel/_psis.py
viabel/_utils.py
viabel/approximations.py
viabel/convenience.py
viabel/diagnostics.py
viabel/models.py
viabel/objectives.py
viabel/optimization.py
viabel-0.5.1.dist-info/LICENSE
viabel-0.5.1.dist-info/METADATA
viabel-0.5.1.dist-info/WHEEL
viabel-0.5.1.dist-info/top_level.txt
viabel-0.5.1.dist-info/RECORD
