Metadata-Version: 2.1
Name: viabel
Version: 0.5.1
Summary: Efficient, lightweight variational inference and approximation bounds
Home-page: https://github.com/jhuggins/viabel/
Author: Jonathan H. Huggins
Author-email: huggins@bu.edu
Platform: ALL
Classifier: Programming Language :: Python :: 3
Classifier: Natural Language :: English
Classifier: License :: OSI Approved :: MIT License
Classifier: Intended Audience :: Science/Research
Classifier: Development Status :: 2 - Pre-Alpha
Classifier: Operating System :: OS Independent
Classifier: Topic :: Scientific/Engineering :: Mathematics
Requires-Python: >=3.5
License-File: LICENSE
Requires-Dist: numpy (>=1.13)
Requires-Dist: scipy
Requires-Dist: autograd
Requires-Dist: tqdm
Requires-Dist: paragami
Provides-Extra: dev
Requires-Dist: codecov ; extra == 'dev'
Requires-Dist: coverage ; extra == 'dev'
Requires-Dist: pytest ; extra == 'dev'
Requires-Dist: pystan (==2.19.1.1) ; extra == 'dev'
Requires-Dist: autoflake ; extra == 'dev'
Requires-Dist: flake8 ; extra == 'dev'
Requires-Dist: isort ; extra == 'dev'
Provides-Extra: docs
Requires-Dist: sphinx (>=1.4) ; extra == 'docs'
Requires-Dist: ipython ; extra == 'docs'
Requires-Dist: matplotlib ; extra == 'docs'
Requires-Dist: seaborn ; extra == 'docs'
Requires-Dist: pystan ; extra == 'docs'
Requires-Dist: numpydoc ; extra == 'docs'
Requires-Dist: sphinx-copybutton ; extra == 'docs'
Requires-Dist: sphinx-rtd-theme ; extra == 'docs'
Requires-Dist: ipykernel ; extra == 'docs'
Requires-Dist: nbsphinx ; extra == 'docs'
Requires-Dist: nbstripout ; extra == 'docs'
